cvapianalyser/CVApiAnalyser.py
cvapianalyser/CommunityEdition.py
cvapianalyser/__init__.py
cvapianalyser/ce_coveragereport.html
cvapianalyser/templates/index.html
cvapianalyser-1.43.7.dist-info/LICENSE.txt
cvapianalyser-1.43.7.dist-info/METADATA
cvapianalyser-1.43.7.dist-info/WHEEL
cvapianalyser-1.43.7.dist-info/entry_points.txt
cvapianalyser-1.43.7.dist-info/top_level.txt
cvapianalyser-1.43.7.dist-info/RECORD
