Metadata-Version: 2.1
Name: cvapianalyser
Version: 1.43.7
Summary: plugin tool for capturing API coverage with input of a SPEC file against API shark of CloudVector
Author: Bala Kumaran
Author-email: balak@cloudvector.com
Requires-Python: >=3.2,<4.0
License-File: LICENSE.txt
Requires-Dist: cvapianalyser
Requires-Dist: jinja2
Requires-Dist: pyyaml
Requires-Dist: requests
